pipelime/__init__.py
pipelime/cli.py
pipelime/pipelime.py
pipelime/cli/__init__.py
pipelime/cli/dump.py
pipelime/cli/main.py
pipelime/cli/summary.py
pipelime/cli/conversions/__init__.py
pipelime/cli/conversions/conversions.py
pipelime/cli/conversions/h5_to_underfolder.py
pipelime/cli/conversions/smart_converter.py
pipelime/cli/conversions/subfolders_to_underfolder.py
pipelime/cli/conversions/underfolder_to_h5.py
pipelime/cli/datasets/__init__.py
pipelime/cli/datasets/datasets.py
pipelime/cli/datasets/generate_toy_dataset.py
pipelime/cli/h5/__init__.py
pipelime/cli/h5/h5.py
pipelime/cli/h5/operations.py
pipelime/cli/piper/__init__.py
pipelime/cli/piper/piper.py
pipelime/cli/underfolder/__init__.py
pipelime/cli/underfolder/operations.py
pipelime/cli/underfolder/underfolder.py
pipelime/cli/workflow/__init__.py
pipelime/cli/workflow/click2cwl.py
pipelime/cli/workflow/delete_nodes.py
pipelime/cli/workflow/init_workflow.py
pipelime/cli/workflow/list_nodes.py
pipelime/cli/workflow/run_workflow.py
pipelime/cli/workflow/show_graph.py
pipelime/cli/workflow/update_nodes.py
pipelime/cli/workflow/workflow.py
pipelime/converters/__init__.py
pipelime/converters/base.py
pipelime/converters/smartconverter.py
pipelime/converters/subfolders2underfolder.py
pipelime/filesystem/__init__.py
pipelime/filesystem/remotes.py
pipelime/filesystem/toolkit.py
pipelime/h5/__init__.py
pipelime/h5/toolkit.py
pipelime/pipes/__init__.py
pipelime/pipes/communication.py
pipelime/pipes/graph.py
pipelime/pipes/locks.py
pipelime/pipes/model.py
pipelime/pipes/piper.py
pipelime/pipes/watcher.py
pipelime/pipes/drawing/__init__.py
pipelime/pipes/drawing/base.py
pipelime/pipes/drawing/factory.py
pipelime/pipes/drawing/graphviz.py
pipelime/pipes/drawing/mermaid.py
pipelime/pipes/executors/__init__.py
pipelime/pipes/executors/base.py
pipelime/pipes/executors/naive.py
pipelime/pipes/parsers/__init__.py
pipelime/pipes/parsers/base.py
pipelime/pipes/parsers/factory.py
pipelime/pipes/parsers/simple.py
pipelime-0.1.8.dist-info/LICENSE
pipelime-0.1.8.dist-info/METADATA
pipelime-0.1.8.dist-info/WHEEL
pipelime-0.1.8.dist-info/entry_points.txt
pipelime-0.1.8.dist-info/top_level.txt
pipelime-0.1.8.dist-info/RECORD
