Metadata-Version: 2.1
Name: pipelime
Version: 0.1.8
Summary: data pipeline 101
Home-page: https://github.com/eyecan-ai/pipelime
Author: daniele de gregorio
Author-email: daniele.degregorio@eyecan.ai
License: GNU General Public License v3
Keywords: pipelime
Classifier: Development Status :: 2 - Pre-Alpha
Classifier: Intended Audience :: Developers
Classifier: License :: OSI Approved :: GNU General Public License v3 (GPLv3)
Classifier: Natural Language :: English
Classifier: Programming Language :: Python :: 3
Classifier: Programming Language :: Python :: 3.5
Classifier: Programming Language :: Python :: 3.6
Classifier: Programming Language :: Python :: 3.7
Classifier: Programming Language :: Python :: 3.8
Requires-Python: >=3.5
License-File: LICENSE
Requires-Dist: click (<8.1,>=8.0.3)
Requires-Dist: rich (>=9.9.0)
Requires-Dist: dictquery
Requires-Dist: schema
Requires-Dist: numpy
Requires-Dist: albumentations (>=0.5.2)
Requires-Dist: choixe (>=0.1.11)
Requires-Dist: imageio
Requires-Dist: pydash
Requires-Dist: Pillow (>=8.0.0)
Requires-Dist: appdirs
Requires-Dist: loguru
Requires-Dist: h5py
Requires-Dist: pydantic
Requires-Dist: fastapi
Requires-Dist: requests
Requires-Dist: joblib
Requires-Dist: deepdiff
Requires-Dist: networkx
Requires-Dist: redis
Requires-Dist: filelock
Provides-Extra: minio
Requires-Dist: minio ; extra == 'minio'
